neolib/__init__.py
neolib/__main__.py
neolib/core_util.py
neolib/crypto_util_bin.py
neolib/decorator.py
neolib/define.py
neolib/file_util.py
neolib/hexstr_util.py
neolib/neo_class.py
neolib/neo_thread_pool.py
neolib/neoserver.py
neolib/neoutil.py
neolib/neoutil4Win.py
neolib/neocopy/__init__.py
neolib/neocopy/__main__.py
neolib/neocopy/release.py
neolib/tool/__init__.py
neolib/tool/__main__.py
neolib/tool/cmd.py
neolib/tool/update_history_and_git.py
neolib_python-2.1.0.dist-info/METADATA
neolib_python-2.1.0.dist-info/WHEEL
neolib_python-2.1.0.dist-info/top_level.txt
neolib_python-2.1.0.dist-info/RECORD
