Metadata-Version: 2.4
Name: neolib-python
Version: 2.1.0
Summary: useful library 4 python developing
Author: neo1seok
Author-email: neo1seok <neo1seok@gmail.com>
License: MIT
Keywords: neolib-python,neolib,neo1seok
Classifier: Development Status :: 3 - Alpha
Classifier: Intended Audience :: Developers
Classifier: License :: OSI Approved :: MIT License
Classifier: Programming Language :: Python
Classifier: Programming Language :: Python :: 3
Classifier: Programming Language :: Python :: 3 :: Only
Classifier: Programming Language :: Python :: 3.8
Classifier: Programming Language :: Python :: 3.9
Classifier: Programming Language :: Python :: 3.10
Classifier: Programming Language :: Python :: 3.11
Classifier: Programming Language :: Python :: 3.12
Classifier: Operating System :: OS Independent
Requires-Python: >=3.8
Requires-Dist: PyYAML>=6.0
Requires-Dist: python-box>=7.0.0
Dynamic: author
